{
    "average": {
        "max": {
            "1": {
                "Member size": 76000,
                "Nonmember size": 22600,
                "ROC AUC Individual": 0.4953768232023805,
                "MIA": {
                    "1": [
                        0.4953768232023805,
                        -5.585543733376723,
                        0.05300139477354667
                    ],
                    "best": {
                        "s": 1,
                        "ROC AUC": 0.4953768232023805,
                        "threshold": -5.585543733376723,
                        "TPR at 5%": 0.05300139477354667
                    }
                }
            },
            "3": {
                "Member size": 25840,
                "Nonmember size": 7684,
                "ROC AUC Individual": 0.4953768232023805,
                "MIA": {
                    "1": [
                        0.49504851714309656,
                        -6.57677599599954,
                        0.04736842105263158
                    ],
                    "3": [
                        0.49477769104651137,
                        -6.139927871580269,
                        0.05008127564052945
                    ],
                    "best": {
                        "s": 1,
                        "ROC AUC": 0.49504851714309656,
                        "threshold": -6.57677599599954,
                        "TPR at 5%": 0.04736842105263158
                    }
                }
            },
            "5": {
                "Member size": 15200,
                "Nonmember size": 4520,
                "ROC AUC Individual": 0.4953768232023805,
                "MIA": {
                    "1": [
                        0.5014728422980785,
                        -7.145406595216846,
                        0.04770050661227712
                    ],
                    "3": [
                        0.4952497165917413,
                        -6.742237107935229,
                        0.0435554970721758
                    ],
                    "5": [
                        0.4967144605659571,
                        -6.336954425467069,
                        0.04118963021450191
                    ],
                    "best": {
                        "s": 1,
                        "ROC AUC": 0.5014728422980785,
                        "threshold": -7.145406595216846,
                        "TPR at 5%": 0.04770050661227712
                    }
                }
            },
            "8": {
                "Member size": 9880,
                "Nonmember size": 2938,
                "ROC AUC Individual": 0.4953768232023805,
                "MIA": {
                    "1": [
                        0.5062689475889021,
                        -7.540974227897016,
                        0.0437246963562753
                    ],
                    "3": [
                        0.4966300507381981,
                        -7.164028433444944,
                        0.04331983805668016
                    ],
                    "5": [
                        0.4938345234715841,
                        -6.862051031397813,
                        0.04159919028340081
                    ],
                    "8": [
                        0.4941755034291053,
                        -6.526316540934232,
                        0.04737801174326787
                    ],
                    "best": {
                        "s": 1,
                        "ROC AUC": 0.5062689475889021,
                        "threshold": -7.540974227897016,
                        "TPR at 5%": 0.0437246963562753
                    }
                }
            },
            "10": {
                "Member size": 7600,
                "Nonmember size": 2260,
                "ROC AUC Individual": 0.4953768232023805,
                "MIA": {
                    "1": [
                        0.513578026684927,
                        -7.907903566272981,
                        0.04316357415449401
                    ],
                    "3": [
                        0.5048284182711512,
                        -7.541661000709728,
                        0.0447427293064877
                    ],
                    "5": [
                        0.4982127364220025,
                        -7.248950019312742,
                        0.04619028819581524
                    ],
                    "8": [
                        0.49630511466925675,
                        -6.884334598941958,
                        0.04619028819581524
                    ],
                    "10": [
                        0.49749573129398283,
                        -6.616092662413523,
                        0.04488023163990524
                    ],
                    "best": {
                        "s": 1,
                        "ROC AUC": 0.513578026684927,
                        "threshold": -7.907903566272981,
                        "TPR at 5%": 0.04316357415449401
                    }
                }
            },
            "30": {
                "Member size": 3040,
                "Nonmember size": 904,
                "ROC AUC Individual": 0.4953768232023805,
                "MIA": {
                    "1": [
                        0.522014184035864,
                        -8.763082287528299,
                        0.0430921052631579
                    ],
                    "3": [
                        0.5223083808802981,
                        -8.154570293494755,
                        0.0375
                    ],
                    "5": [
                        0.5148462971588262,
                        -7.690387177323794,
                        0.034210526315789476
                    ],
                    "8": [
                        0.5067881782720075,
                        -7.250156696641457,
                        0.037171052631578945
                    ],
                    "10": [
                        0.5043756549836982,
                        -6.978156061502217,
                        0.04375
                    ],
                    "30": [
                        0.49334826708302504,
                        -6.811084070569519,
                        0.04180381830151415
                    ],
                    "best": {
                        "s": 3,
                        "ROC AUC": 0.5223083808802981,
                        "threshold": -8.154570293494755,
                        "TPR at 5%": 0.0375
                    }
                }
            },
            "50": {
                "Member size": 1520,
                "Nonmember size": 452,
                "ROC AUC Individual": 0.4953768232023805,
                "MIA": {
                    "1": [
                        0.5304763914764787,
                        -10.306486441710284,
                        0.05921052631578947
                    ],
                    "3": [
                        0.5470234629715882,
                        -10.007944889677427,
                        0.08157894736842106
                    ],
                    "5": [
                        0.5456028761061946,
                        -9.589332544101026,
                        0.07171052631578947
                    ],
                    "8": [
                        0.5359862598975313,
                        -9.188368898812321,
                        0.07302631578947369
                    ],
                    "10": [
                        0.5279226828132277,
                        -8.93036236769178,
                        0.06381578947368421
                    ],
                    "30": [
                        0.49619672799254777,
                        -7.695848799458445,
                        0.057236842105263155
                    ],
                    "50": [
                        0.49634766285401144,
                        -7.023502550229114,
                        0.0691699604743083
                    ],
                    "best": {
                        "s": 3,
                        "ROC AUC": 0.5470234629715882,
                        "threshold": -10.007944889677427,
                        "TPR at 5%": 0.08157894736842106
                    }
                }
            },
            "80": {
                "Member size": 1520,
                "Nonmember size": 452,
                "ROC AUC Individual": 0.4953768232023805,
                "MIA": {
                    "1": [
                        0.5270981311131812,
                        -9.57472470768711,
                        0.060526315789473685
                    ],
                    "3": [
                        0.5280260246856079,
                        -8.938238573134788,
                        0.05460526315789474
                    ],
                    "5": [
                        0.5204893455985096,
                        -8.525936523491396,
                        0.05592105263157895
                    ],
                    "8": [
                        0.5147313111318118,
                        -8.042880836817709,
                        0.049342105263157895
                    ],
                    "10": [
                        0.5119818351187704,
                        -7.8413014035395125,
                        0.056578947368421055
                    ],
                    "30": [
                        0.49970889613414066,
                        -6.988709991956542,
                        0.05526315789473684
                    ],
                    "50": [
                        0.49513099558978596,
                        -6.988709991956542,
                        0.055299539170506916
                    ],
                    "80": [
                        0.49525604253384164,
                        -6.964402474305108,
                        0.05401844532279315
                    ],
                    "best": {
                        "s": 3,
                        "ROC AUC": 0.5280260246856079,
                        "threshold": -8.938238573134788,
                        "TPR at 5%": 0.05460526315789474
                    }
                }
            },
            "100": {
                "Member size": 760,
                "Nonmember size": 226,
                "ROC AUC Individual": 0.4953768232023805,
                "MIA": {
                    "1": [
                        0.5326298323241732,
                        -11.39193694487862,
                        0.06315789473684211
                    ],
                    "3": [
                        0.5571844434094084,
                        -10.894532400652233,
                        0.06184210526315789
                    ],
                    "5": [
                        0.555082673497904,
                        -10.602987207613584,
                        0.07105263157894737
                    ],
                    "8": [
                        0.553615510013973,
                        -10.178631801542489,
                        0.056578947368421055
                    ],
                    "10": [
                        0.5548847228691197,
                        -10.019984731503566,
                        0.07105263157894737
                    ],
                    "30": [
                        0.515836050302748,
                        -8.666338896461435,
                        0.056578947368421055
                    ],
                    "50": [
                        0.49871745543157625,
                        -8.06361095850595,
                        0.057971014492753624
                    ],
                    "80": [
                        0.4930567700863968,
                        -7.419186674650291,
                        0.03557312252964427
                    ],
                    "100": [
                        0.49705209330562494,
                        -7.087799406996543,
                        0.04353562005277045
                    ],
                    "best": {
                        "s": 3,
                        "ROC AUC": 0.5571844434094084,
                        "threshold": -10.894532400652233,
                        "TPR at 5%": 0.06184210526315789
                    }
                }
            }
        },
        "min": {
            "1": {
                "Member size": 76000,
                "Nonmember size": 22600,
                "ROC AUC Individual": 0.4953768232023805,
                "MIA": {
                    "1": [
                        0.4953768232023805,
                        -5.585543733376723,
                        0.05300139477354667
                    ],
                    "best": {
                        "s": 1,
                        "ROC AUC": 0.4953768232023805,
                        "threshold": -5.585543733376723,
                        "TPR at 5%": 0.05300139477354667
                    }
                }
            },
            "3": {
                "Member size": 25840,
                "Nonmember size": 7684,
                "ROC AUC Individual": 0.4953768232023805,
                "MIA": {
                    "1": [
                        0.4987464805643345,
                        -5.179152573303527,
                        0.055108359133126936
                    ],
                    "3": [
                        0.49477769104651137,
                        -6.139927871580269,
                        0.05008127564052945
                    ],
                    "best": {
                        "s": 1,
                        "ROC AUC": 0.4987464805643345,
                        "threshold": -5.179152573303527,
                        "TPR at 5%": 0.055108359133126936
                    }
                }
            },
            "5": {
                "Member size": 15200,
                "Nonmember size": 4520,
                "ROC AUC Individual": 0.4953768232023805,
                "MIA": {
                    "1": [
                        0.4999739881582801,
                        -4.935794656960349,
                        0.05401671162576485
                    ],
                    "3": [
                        0.49412690537995796,
                        -5.751351041630993,
                        0.04836162652980655
                    ],
                    "5": [
                        0.4967144605659571,
                        -6.33695442546707,
                        0.04118963021450191
                    ],
                    "best": {
                        "s": 1,
                        "ROC AUC": 0.4999739881582801,
                        "threshold": -4.935794656960349,
                        "TPR at 5%": 0.05401671162576485
                    }
                }
            },
            "8": {
                "Member size": 9880,
                "Nonmember size": 2938,
                "ROC AUC Individual": 0.4953768232023805,
                "MIA": {
                    "1": [
                        0.5071976084206372,
                        -4.7251419139234985,
                        0.04980261160036441
                    ],
                    "3": [
                        0.49875568387699576,
                        -5.520890909508132,
                        0.04828912735371533
                    ],
                    "5": [
                        0.49106330037898716,
                        -5.9174924898113,
                        0.051224944320712694
                    ],
                    "8": [
                        0.4941755034291053,
                        -6.526316540934232,
                        0.04737801174326787
                    ],
                    "best": {
                        "s": 1,
                        "ROC AUC": 0.5071976084206372,
                        "threshold": -4.7251419139234985,
                        "TPR at 5%": 0.04980261160036441
                    }
                }
            },
            "10": {
                "Member size": 7600,
                "Nonmember size": 2260,
                "ROC AUC Individual": 0.4953768232023805,
                "MIA": {
                    "1": [
                        0.5038776061591709,
                        -4.625330123089967,
                        0.05184892749045927
                    ],
                    "3": [
                        0.5000349952893196,
                        -5.421818075700653,
                        0.0548756415317805
                    ],
                    "5": [
                        0.4930847910821987,
                        -5.77815225093658,
                        0.052638505066456114
                    ],
                    "8": [
                        0.48460738387139607,
                        -6.2355439740109295,
                        0.05356672808633851
                    ],
                    "10": [
                        0.49749573129398283,
                        -6.616092662413523,
                        0.04488023163990524
                    ],
                    "best": {
                        "s": 1,
                        "ROC AUC": 0.5038776061591709,
                        "threshold": -4.625330123089967,
                        "TPR at 5%": 0.05184892749045927
                    }
                }
            },
            "30": {
                "Member size": 3040,
                "Nonmember size": 904,
                "ROC AUC Individual": 0.4953768232023805,
                "MIA": {
                    "1": [
                        0.5178931268145378,
                        -4.284070230882192,
                        0.055281342546890426
                    ],
                    "3": [
                        0.5119723098247851,
                        -4.945850989406501,
                        0.04606778545574202
                    ],
                    "5": [
                        0.5066433561342664,
                        -5.255145012917396,
                        0.04639684106614018
                    ],
                    "8": [
                        0.4980923785443381,
                        -5.549938427060597,
                        0.04707044107965767
                    ],
                    "10": [
                        0.49548127843772394,
                        -5.694510438348374,
                        0.04805793285055958
                    ],
                    "30": [
                        0.49334826708302504,
                        -6.811084070569519,
                        0.04180381830151415
                    ],
                    "best": {
                        "s": 1,
                        "ROC AUC": 0.5178931268145378,
                        "threshold": -4.284070230882192,
                        "TPR at 5%": 0.055281342546890426
                    }
                }
            },
            "50": {
                "Member size": 1520,
                "Nonmember size": 452,
                "ROC AUC Individual": 0.4953768232023805,
                "MIA": {
                    "1": [
                        0.5123107824871914,
                        -3.801450533726476,
                        0.04407894736842105
                    ],
                    "3": [
                        0.5152710249863002,
                        -4.612910931570072,
                        0.050724637681159424
                    ],
                    "5": [
                        0.5145291895484276,
                        -5.001123630660408,
                        0.05731225296442688
                    ],
                    "8": [
                        0.512864796483496,
                        -5.301774374557754,
                        0.059947299077733864
                    ],
                    "10": [
                        0.5089486632387747,
                        -5.412719364200675,
                        0.05533596837944664
                    ],
                    "30": [
                        0.48638462345657424,
                        -6.129082469178468,
                        0.046772068511198944
                    ],
                    "50": [
                        0.49634766285401144,
                        -7.023502550229114,
                        0.0691699604743083
                    ],
                    "best": {
                        "s": 3,
                        "ROC AUC": 0.5152710249863002,
                        "threshold": -4.612910931570072,
                        "TPR at 5%": 0.050724637681159424
                    }
                }
            },
            "80": {
                "Member size": 1520,
                "Nonmember size": 452,
                "ROC AUC Individual": 0.4953768232023805,
                "MIA": {
                    "1": [
                        0.5135406963204472,
                        -3.8614085726907024,
                        0.04473684210526316
                    ],
                    "3": [
                        0.5126611592396022,
                        -4.586595111112829,
                        0.04805793285055958
                    ],
                    "5": [
                        0.5058953327037206,
                        -4.90508852302275,
                        0.050724637681159424
                    ],
                    "8": [
                        0.4995598540231091,
                        -5.185863545196526,
                        0.05006587615283267
                    ],
                    "10": [
                        0.49670327748434717,
                        -5.304746838319062,
                        0.05006587615283267
                    ],
                    "30": [
                        0.4961261324285564,
                        -5.8812571180323205,
                        0.04018445322793149
                    ],
                    "50": [
                        0.49332785337017737,
                        -6.262189231241007,
                        0.050724637681159424
                    ],
                    "80": [
                        0.49525604253384164,
                        -6.964402474305108,
                        0.05401844532279315
                    ],
                    "best": {
                        "s": 1,
                        "ROC AUC": 0.5135406963204472,
                        "threshold": -3.8614085726907024,
                        "TPR at 5%": 0.04473684210526316
                    }
                }
            },
            "100": {
                "Member size": 760,
                "Nonmember size": 226,
                "ROC AUC Individual": 0.4953768232023805,
                "MIA": {
                    "1": [
                        0.502241499767117,
                        -3.3621117510750045,
                        0.046052631578947366
                    ],
                    "3": [
                        0.5115289420225557,
                        -4.337216079663114,
                        0.06200527704485488
                    ],
                    "5": [
                        0.5144943610339272,
                        -4.695016739565017,
                        0.06464379947229551
                    ],
                    "8": [
                        0.5187440166250263,
                        -4.993343391763052,
                        0.0633245382585752
                    ],
                    "10": [
                        0.5182945338221215,
                        -5.131150197735768,
                        0.06860158311345646
                    ],
                    "30": [
                        0.49810866976440094,
                        -5.7302316952611365,
                        0.059366754617414245
                    ],
                    "50": [
                        0.4863929296938847,
                        -6.056716822474659,
                        0.059366754617414245
                    ],
                    "80": [
                        0.46274546430989794,
                        -6.500137005863155,
                        0.05408970976253298
                    ],
                    "100": [
                        0.49705209330562494,
                        -7.0877994069965435,
                        0.04353562005277045
                    ],
                    "best": {
                        "s": 8,
                        "ROC AUC": 0.5187440166250263,
                        "threshold": -4.993343391763052,
                        "TPR at 5%": 0.0633245382585752
                    }
                }
            }
        },
        "Total individual ROC AUC": 0.49554419165207997
    },
    "std": 0
}